ora_check/__init__.py
ora_check/__main__.py
ora_check/config_oracle.yaml
ora_check/css/jquery-3.7.0.js
ora_check/css/jquery.dataTables.min.css
ora_check/css/jquery.dataTables.min.js
dms_check-0.1.4.dist-info/LICENSE
dms_check-0.1.4.dist-info/METADATA
dms_check-0.1.4.dist-info/WHEEL
dms_check-0.1.4.dist-info/entry_points.txt
dms_check-0.1.4.dist-info/RECORD
