Metadata-Version: 2.1
Name: dms_check
Version: 0.1.4
Summary: Check compatibility of Oracle Database with DMS migrations
License: Google
Author: sametkaradag
Author-email: sametkaradag@gmail.com
Requires-Python: >=3.9,<4.0
Classifier: License :: Other/Proprietary License
Classifier: Programming Language :: Python :: 3
Classifier: Programming Language :: Python :: 3.9
Classifier: Programming Language :: Python :: 3.10
Classifier: Programming Language :: Python :: 3.11
Classifier: Programming Language :: Python :: 3.12
Requires-Dist: google-cloud-secret-manager (>=2.21.1,<3.0.0)
Requires-Dist: oracledb (>=2.3.0,<3.0.0)
Requires-Dist: pyyaml (==6.0.1)
